devcontainer_contrib/__init__.py
devcontainer_contrib/__main__.py
devcontainer_contrib/settings.py
devcontainer_contrib/cli/__init__.py
devcontainer_contrib/cli/feature.py
devcontainer_contrib/cli/features.py
devcontainer_contrib/cli/download/download_feature.py
devcontainer_contrib/cli/generate/__init__.py
devcontainer_contrib/cli/generate/generate.py
devcontainer_contrib/cli/generate/generate_feature.py
devcontainer_contrib/cli/generate/dir_models/__init__.py
devcontainer_contrib/cli/generate/dir_models/src_dir.py
devcontainer_contrib/cli/generate/dir_models/test_dir.py
devcontainer_contrib/cli/generate/file_models/__init__.py
devcontainer_contrib/cli/generate/file_models/dependencies_sh.py
devcontainer_contrib/cli/generate/file_models/devcontainer_feature_json.py
devcontainer_contrib/cli/generate/file_models/install_command_sh.py
devcontainer_contrib/cli/generate/file_models/install_sh.py
devcontainer_contrib/cli/generate/file_models/scenarios_json.py
devcontainer_contrib/cli/generate/file_models/test_sh.py
devcontainer_contrib/cli/inspect/__init__.py
devcontainer_contrib/cli/inspect/extract_devcontainer_feature_obj.py
devcontainer_contrib/cli/install/__init__.py
devcontainer_contrib/cli/install/install.py
devcontainer_contrib/cli/install/install_feature.py
devcontainer_contrib/features_generation/__init__.py
devcontainer_contrib/features_generation/dir_modules/__init__.py
devcontainer_contrib/features_generation/dir_modules/src_dir.py
devcontainer_contrib/features_generation/dir_modules/test_dir.py
devcontainer_contrib/features_generation/file_models/__init__.py
devcontainer_contrib/features_generation/file_models/dependencies_sh.py
devcontainer_contrib/features_generation/file_models/devcontainer_feature_json.py
devcontainer_contrib/features_generation/file_models/install_command_sh.py
devcontainer_contrib/features_generation/file_models/install_sh.py
devcontainer_contrib/features_generation/file_models/scenarios_json.py
containerful-0.0.1.dist-info/METADATA
containerful-0.0.1.dist-info/WHEEL
containerful-0.0.1.dist-info/entry_points.txt
containerful-0.0.1.dist-info/top_level.txt
containerful-0.0.1.dist-info/RECORD
