Metadata-Version: 2.1
Name: containerful
Version: 0.0.1
Requires-Dist: pydantic (==1.10.5)
Requires-Dist: typer
Requires-Dist: python-dxf
Requires-Dist: invoke
Provides-Extra: dev
Requires-Dist: pytest ; extra == 'dev'
Requires-Dist: pytest-shell-utilities ; extra == 'dev'
Requires-Dist: black ; extra == 'dev'
Requires-Dist: mypy ; extra == 'dev'
Provides-Extra: generate
Requires-Dist: easyfs (==0.0.3) ; extra == 'generate'
